.gitignore
MANIFEST.in
Makefile
README.md
setup.py
tox.ini
development/app_streamlit.py
development/generate_examples.py
development/header_image.jpg
development/header_image.xcf
development/examples/1977.jpg
development/examples/Aden.jpg
development/examples/Amaro.jpg
development/examples/Ashby.jpg
development/examples/Brannan.jpg
development/examples/Brooklyn.jpg
development/examples/Charmes.jpg
development/examples/Clarendon.jpg
development/examples/Crema.jpg
development/examples/Dogpatch.jpg
development/examples/Earlybird.jpg
development/examples/Gingham.jpg
development/examples/Ginza.jpg
development/examples/Hefe.jpg
development/examples/Helena.jpg
development/examples/Hudson.jpg
development/examples/Inkwell.jpg
development/examples/Juno.jpg
development/examples/Kelvin.jpg
development/examples/Lark.jpg
development/examples/Lo-Fi.jpg
development/examples/Ludwig.jpg
development/examples/Mayfair.jpg
development/examples/Melvin.jpg
development/examples/Moon.jpg
development/examples/Nashville.jpg
development/examples/Normal.jpg
development/examples/Perpetua.jpg
development/examples/Reyes.jpg
development/examples/Rise.jpg
development/examples/Sierra.jpg
development/examples/Skyline.jpg
development/examples/Slumber.jpg
development/examples/Stinson.jpg
development/examples/Sutro.jpg
development/examples/Toaster.jpg
development/examples/Valencia.jpg
development/examples/Vesper.jpg
development/examples/Walden.jpg
development/examples/Willow.jpg
development/examples/X-ProII.jpg
development/train_new_model/LR_finder.py
development/train_new_model/dataset.py
development/train_new_model/instafilter
development/train_new_model/train.py
development/train_new_model/input/1977.jpg
development/train_new_model/input/Aden.jpg
development/train_new_model/input/Amaro.jpg
development/train_new_model/input/Ashby.jpg
development/train_new_model/input/Brannan.jpg
development/train_new_model/input/Brooklyn.jpg
development/train_new_model/input/Charmes.jpg
instafilter.egg-info/PKG-INFO
instafilter.egg-info/SOURCES.txt
instafilter.egg-info/dependency_links.txt
instafilter.egg-info/requires.txt
instafilter.egg-info/top_level.txt
