Metadata-Version: 2.1
Name: instafilter
Version: 0.3.2
Summary: Images filters learned from Instagram. Implemented in pytorch.
Home-page: https://github.com/thoppe/instafilter
Author: Travis Hoppe
Author-email: travis.hoppe+{package_name}@gmail.com
License: CC-SA
Keywords: art
Platform: UNKNOWN
Classifier: Development Status :: 4 - Beta
Classifier: Environment :: GPU
Classifier: Intended Audience :: Developers
Classifier: Intended Audience :: Other Audience
Classifier: Intended Audience :: Science/Research
Classifier: Topic :: Artistic Software
Classifier: Programming Language :: Python :: 3.6
